glfwToolbox/__init__.py
glfwToolbox/about.py
glfwToolbox/advanced_shapes.py
glfwToolbox/camera.py
glfwToolbox/catrom.py
glfwToolbox/colors.py
glfwToolbox/easy_shaders.py
glfwToolbox/lights.py
glfwToolbox/materials.py
glfwToolbox/mathlib.py
glfwToolbox/opengl.py
glfwToolbox/scene_graph.py
glfwToolbox/shapes.py
glfwToolbox/transformations.py
glfwToolbox/tripy.py
glfw_toolbox-1.1.0.dist-info/LICENSE
glfw_toolbox-1.1.0.dist-info/METADATA
glfw_toolbox-1.1.0.dist-info/WHEEL
glfw_toolbox-1.1.0.dist-info/top_level.txt
glfw_toolbox-1.1.0.dist-info/RECORD
