Metadata-Version: 2.1
Name: glfw-toolbox
Version: 1.1.0
Summary: GLFW toolbox
Home-page: https://github.com/ppizarror/glfw-toolbox
Author: Pablo Pizarro @ppizarror.com
Author-email: pablo@ppizarror.com
License: MIT
Platform: UNKNOWN
Classifier: License :: OSI Approved :: MIT License
Classifier: Operating System :: OS Independent
Classifier: Programming Language :: Python
Requires-Python: >3.5
Requires-Dist: numpy
Requires-Dist: PyOpenGL
Requires-Dist: glfw
Requires-Dist: Pillow
Requires-Dist: matplotlib
